tiny_keccak-0.4.0.dist-info/METADATA
tiny_keccak-0.4.0.dist-info/WHEEL
tiny_keccak-0.4.0.dist-info/licenses/LICENSE
tiny_keccak/__init__.py
tiny_keccak/__init__.pyi
tiny_keccak/py.typed
tiny_keccak/tiny_keccak.abi3.so
tiny_keccak-0.4.0.dist-info/RECORD
